myfirstpypidemo.py
withaverylongpackagename/__init__.py
withaverylongpackagename/myfirstsubpypidemo.py
zrchnpypidemo-0.3.5.dist-info/LICENSE
zrchnpypidemo-0.3.5.dist-info/METADATA
zrchnpypidemo-0.3.5.dist-info/WHEEL
zrchnpypidemo-0.3.5.dist-info/top_level.txt
zrchnpypidemo-0.3.5.dist-info/RECORD
