Metadata-Version: 2.1
Name: zrchnpypidemo
Version: 0.3.5
Summary: My first pypi demo.
Home-page: https://github.com/RuiZhangCHN/MyFirstPypiDemo
Author: RuiZhangCHN
Author-email: zhang1rui4@foxmail.com
License: MIT
Platform: UNKNOWN
Classifier: License :: OSI Approved :: MIT License
Classifier: Programming Language :: Python
Classifier: Programming Language :: Python :: 3
Classifier: Programming Language :: Python :: 3.6
Classifier: Programming Language :: Python :: Implementation :: CPython
Classifier: Programming Language :: Python :: Implementation :: PyPy
Requires-Python: >=3.6.0
